oampy/__init__.py
oampy/__main__.py
oampy/client.py
oampy/docs.py
oampy/query.py
oampy/utils.py
oampy-0.3.0.dist-info/licenses/LICENSE
oampy-0.3.0.dist-info/METADATA
oampy-0.3.0.dist-info/WHEEL
oampy-0.3.0.dist-info/top_level.txt
oampy-0.3.0.dist-info/RECORD
