Metadata-Version: 2.4
Name: oampy
Version: 0.3.0
Summary: Open Access Monitor API Client
Author-email: Donatus Herre <donatus.herre@slub-dresden.de>
License:                     GNU GENERAL PUBLIC LICENSE
Project-URL: Homepage, https://github.com/herreio/oampy
Project-URL: Repository, https://github.com/herreio/oampy.git
Project-URL: Issues, https://github.com/herreio/oampy/issues
Project-URL: Changelog, https://github.com/herreio/oampy/blob/main/CHANGELOG
License-File: LICENSE
Requires-Dist: requests
Requires-Dist: click
Dynamic: license-file
